mpy_file_info/__init__.py
mpy_file_info/__main__.py
mpy_file_info/makeqstrdata.py
mpy_file_info/mpy_tool.py
mpy_file_info-0.1.2.dist-info/METADATA
mpy_file_info-0.1.2.dist-info/WHEEL
mpy_file_info-0.1.2.dist-info/entry_points.txt
mpy_file_info-0.1.2.dist-info/licenses/LICENSE
mpy_file_info-0.1.2.dist-info/RECORD
