Metadata-Version: 2.4
Name: mpy-file-info
Version: 0.1.2
Summary: A program to run MicroPython mpy-tool
Author-email: David Walker <dbwalker0min@gmail.com>
License: MIT
License-File: LICENSE
Requires-Python: >=3.13
